src/__init__.py
src/project_ingestor.py
src/server.py
project_ingest_mcp-1.0.2.dist-info/METADATA
project_ingest_mcp-1.0.2.dist-info/WHEEL
project_ingest_mcp-1.0.2.dist-info/entry_points.txt
project_ingest_mcp-1.0.2.dist-info/licenses/LICENSE
project_ingest_mcp-1.0.2.dist-info/RECORD
